colour_fx/__init__.py
colour_fx/eight_bit.py
colour_fx/four_bit.py
colour_fx/effects/__init__.py
colour_fx/effects/gradients.py
colour_fx-2.0.0.dist-info/METADATA
colour_fx-2.0.0.dist-info/WHEEL
colour_fx-2.0.0.dist-info/licenses/LICENSE
colour_fx-2.0.0.dist-info/RECORD
