Metadata-Version: 2.3
Name: colour_fx
Version: 2.0.0
Summary: Colour handling through 4 bit and 8 bit ANSI escape sequences. Powerful effects like gradients for blocks of text such as figlet banners.
Project-URL: Homepage, https://github.com/Max-Derner/colour_fx
Project-URL: Issues, https://github.com/Max-Derner/colour_fx/issues
Author-email: Max Derner <max.derner@gmail.com>
Classifier: License :: OSI Approved :: MIT License
Classifier: Operating System :: OS Independent
Classifier: Programming Language :: Python :: 3
Requires-Python: >=3.9
